{
  "version": 2,
  "stageSize": {
    "width": 1360,
    "height": 1760
  },
  "backgroundDataUrl": "",
  "pdfPage": 19,
  "placed": [
    {
      "page": 1,
      "uid": "c1",
      "kind": "card",
      "cardId": "bp_club_base",
      "registryId": "bp_club_base",
      "name": "Чертеж на дубину",
      "deck": "base",
      "art": "generated-frame-highres-text/base/base-001-style-v1-card-highres-text",
      "face": "front",
      "x": 57,
      "y": 635,
      "w": 180
    },
    {
      "page": 1,
      "uid": "c2",
      "kind": "back",
      "cardId": "back:base",
      "registryId": "back:base",
      "name": "Базовые карты",
      "deck": "base",
      "art": "backs/base-cards",
      "face": "back",
      "x": 925,
      "y": 335,
      "w": 180
    },
    {
      "page": 1,
      "uid": "c3",
      "kind": "back",
      "cardId": "back:base",
      "registryId": "back:base",
      "name": "Базовые карты",
      "deck": "base",
      "art": "backs/base-cards",
      "face": "back",
      "x": 579,
      "y": 804,
      "w": 180
    },
    {
      "page": 1,
      "uid": "c4",
      "kind": "card",
      "cardId": "club",
      "registryId": "club",
      "name": "Дубина",
      "deck": "base",
      "art": "generated-frame-highres-text/base/base-002-style-v1-card-highres-text",
      "face": "front",
      "x": 926,
      "y": 680,
      "w": 180
    },
    {
      "page": 1,
      "uid": "c5",
      "kind": "card",
      "cardId": "teleport_beads",
      "registryId": "teleport_beads",
      "name": "Бусы телепортации",
      "deck": "base",
      "art": "generated-frame-highres-text/base/base-003-style-v1-card-highres-text",
      "face": "front",
      "x": 570,
      "y": 1211,
      "w": 180
    },
    {
      "page": 1,
      "uid": "c6",
      "kind": "back",
      "cardId": "back:base",
      "registryId": "back:base",
      "name": "Базовые карты",
      "deck": "base",
      "art": "backs/base-cards",
      "face": "back",
      "x": 183,
      "y": 1283,
      "w": 180
    },
    {
      "page": 2,
      "uid": "c7",
      "kind": "back",
      "cardId": "back:base",
      "registryId": "back:base",
      "name": "Базовые карты",
      "deck": "base",
      "art": "backs/base-cards",
      "face": "back",
      "x": 925,
      "y": 217,
      "w": 180
    },
    {
      "page": 2,
      "uid": "c8",
      "kind": "card",
      "cardId": "yarn",
      "registryId": "yarn",
      "name": "Клубок сплетенной нити из шерсти барана",
      "deck": "base",
      "art": "generated-frame-highres-text/base/base-004-style-v1-card-highres-text",
      "face": "front",
      "x": 142,
      "y": 666,
      "w": 180
    },
    {
      "page": 2,
      "uid": "c9",
      "kind": "card",
      "cardId": "shaman_carpet",
      "registryId": "shaman_carpet",
      "name": "Ковер шамана",
      "deck": "base",
      "art": "generated-frame-highres-text/base/base-005-style-v1-card-highres-text",
      "face": "front",
      "x": 1179,
      "y": 625,
      "w": 180
    },
    {
      "page": 2,
      "uid": "c10",
      "kind": "back",
      "cardId": "back:base",
      "registryId": "back:base",
      "name": "Базовые карты",
      "deck": "base",
      "art": "backs/base-cards",
      "face": "back",
      "x": 558,
      "y": 729,
      "w": 180
    },
    {
      "page": 2,
      "uid": "c11",
      "kind": "back",
      "cardId": "back:base",
      "registryId": "back:base",
      "name": "Базовые карты",
      "deck": "base",
      "art": "backs/base-cards",
      "face": "back",
      "x": 203,
      "y": 1228,
      "w": 180
    },
    {
      "page": 2,
      "uid": "c12",
      "kind": "card",
      "cardId": "recipe_shaman_carpet",
      "registryId": "recipe_shaman_carpet",
      "name": "Рецепт на ковер шамана",
      "deck": "base",
      "art": "generated-frame-highres-text/base/base-006-style-v1-card-highres-text",
      "face": "front",
      "x": 1461,
      "y": 954,
      "w": 180
    },
    {
      "page": 2,
      "uid": "c13",
      "kind": "back",
      "cardId": "back:base",
      "registryId": "back:base",
      "name": "Базовые карты",
      "deck": "base",
      "art": "backs/base-cards",
      "face": "back",
      "x": 929,
      "y": 1314,
      "w": 180
    },
    {
      "page": 3,
      "uid": "c14",
      "kind": "card",
      "cardId": "sheep_hide_c",
      "registryId": "sheep_hide_c",
      "name": "Очищенная шкура барана",
      "deck": "base",
      "art": "generated-frame-highres-text/base/base-007-style-v1-card-highres-text",
      "face": "front",
      "x": 159,
      "y": 90,
      "w": 180
    },
    {
      "page": 3,
      "uid": "c15",
      "kind": "back",
      "cardId": "back:base",
      "registryId": "back:base",
      "name": "Базовые карты",
      "deck": "base",
      "art": "backs/base-cards",
      "face": "back",
      "x": 576,
      "y": 177,
      "w": 180
    },
    {
      "page": 3,
      "uid": "c16",
      "kind": "card",
      "cardId": "sheep_wool",
      "registryId": "sheep_wool",
      "name": "Шерсть барана",
      "deck": "base",
      "art": "generated-frame-highres-text/base/base-008-style-v1-card-highres-text",
      "face": "front",
      "x": 1032,
      "y": 41,
      "w": 180
    },
    {
      "page": 3,
      "uid": "c17",
      "kind": "back",
      "cardId": "back:base",
      "registryId": "back:base",
      "name": "Базовые карты",
      "deck": "base",
      "art": "backs/base-cards",
      "face": "back",
      "x": 169,
      "y": 661,
      "w": 180
    },
    {
      "page": 3,
      "uid": "c18",
      "kind": "card",
      "cardId": "sheep_hide_r",
      "registryId": "sheep_hide_r",
      "name": "Шкура барана",
      "deck": "base",
      "art": "generated-frame-highres-text/base/base-009-style-v1-card-highres-text",
      "face": "front",
      "x": 569,
      "y": 643,
      "w": 171
    },
    {
      "page": 3,
      "uid": "c19",
      "kind": "card",
      "cardId": "sheep_ram",
      "registryId": "sheep_ram",
      "name": "Баран",
      "deck": "base",
      "art": "generated-frame-highres-text/base/base-010-style-v1-card-highres-text",
      "face": "front",
      "x": 102,
      "y": 1099,
      "w": 180
    },
    {
      "page": 3,
      "uid": "c20",
      "kind": "back",
      "cardId": "back:base",
      "registryId": "back:base",
      "name": "Базовые карты",
      "deck": "base",
      "art": "backs/base-cards",
      "face": "back",
      "x": 944,
      "y": 672,
      "w": 180
    },
    {
      "page": 3,
      "uid": "c21",
      "kind": "card",
      "cardId": "teleport_beads",
      "registryId": "teleport_beads",
      "name": "Бусы телепортации",
      "deck": "base",
      "art": "generated-frame-highres-text/base/base-003-style-v1-card-highres-text",
      "face": "front",
      "x": 972,
      "y": 1149,
      "w": 180
    },
    {
      "page": 3,
      "uid": "c22",
      "kind": "back",
      "cardId": "back:base",
      "registryId": "back:base",
      "name": "Базовые карты",
      "deck": "base",
      "art": "backs/base-cards",
      "face": "back",
      "x": 579,
      "y": 1177,
      "w": 180
    },
    {
      "page": 4,
      "uid": "c23",
      "kind": "card",
      "cardId": "recipe_sack",
      "registryId": "recipe_sack",
      "name": "Рецепт на мешок",
      "deck": "base",
      "art": "generated-frame-highres-text/base/base-011-style-v1-card-highres-text",
      "face": "front",
      "x": 103,
      "y": 570,
      "w": 124
    },
    {
      "page": 4,
      "uid": "c24",
      "kind": "back",
      "cardId": "back:base",
      "registryId": "back:base",
      "name": "Базовые карты",
      "deck": "base",
      "art": "backs/base-cards",
      "face": "back",
      "x": 1008,
      "y": 146,
      "w": 124
    },
    {
      "page": 4,
      "uid": "c25",
      "kind": "back",
      "cardId": "back:base",
      "registryId": "back:base",
      "name": "Базовые карты",
      "deck": "base",
      "art": "backs/base-cards",
      "face": "back",
      "x": 607,
      "y": 682,
      "w": 124
    },
    {
      "page": 4,
      "uid": "c26",
      "kind": "card",
      "cardId": "sack",
      "registryId": "sack",
      "name": "Мешок",
      "deck": "base",
      "art": "generated-frame-highres-text/base/base-012-style-v1-card-highres-text",
      "face": "front",
      "x": 1189,
      "y": 572,
      "w": 124
    },
    {
      "page": 4,
      "uid": "c27",
      "kind": "back",
      "cardId": "back:base",
      "registryId": "back:base",
      "name": "Базовые карты",
      "deck": "base",
      "art": "backs/base-cards",
      "face": "back",
      "x": 216,
      "y": 1250,
      "w": 124
    },
    {
      "page": 4,
      "uid": "c28",
      "kind": "card",
      "cardId": "yarn",
      "registryId": "yarn",
      "name": "Клубок сплетенной нити из шерсти барана",
      "deck": "base",
      "art": "generated-frame-highres-text/base/base-004-style-v1-card-highres-text",
      "face": "front",
      "x": 596,
      "y": 1201,
      "w": 124
    },
    {
      "page": 4,
      "uid": "c29",
      "kind": "back",
      "cardId": "back:base",
      "registryId": "back:base",
      "name": "Базовые карты",
      "deck": "base",
      "art": "backs/base-cards",
      "face": "back",
      "x": 955,
      "y": 1287,
      "w": 92
    },
    {
      "page": 5,
      "uid": "c30",
      "kind": "card",
      "cardId": "sheep_hide_c",
      "registryId": "sheep_hide_c",
      "name": "Очищенная шкура барана",
      "deck": "base",
      "art": "generated-frame-highres-text/base/base-007-style-v1-card-highres-text",
      "face": "front",
      "x": 222,
      "y": 120,
      "w": 92
    },
    {
      "page": 5,
      "uid": "c31",
      "kind": "card",
      "cardId": "sheep_wool",
      "registryId": "sheep_wool",
      "name": "Шерсть барана",
      "deck": "base",
      "art": "generated-frame-highres-text/base/base-008-style-v1-card-highres-text",
      "face": "front",
      "x": 989,
      "y": 208,
      "w": 92
    },
    {
      "page": 5,
      "uid": "c32",
      "kind": "back",
      "cardId": "back:base",
      "registryId": "back:base",
      "name": "Базовые карты",
      "deck": "base",
      "art": "backs/base-cards",
      "face": "back",
      "x": 636,
      "y": 204,
      "w": 92
    },
    {
      "page": 5,
      "uid": "c33",
      "kind": "back",
      "cardId": "back:base",
      "registryId": "back:base",
      "name": "Базовые карты",
      "deck": "base",
      "art": "backs/base-cards",
      "face": "back",
      "x": 189,
      "y": 684,
      "w": 92
    },
    {
      "page": 5,
      "uid": "c34",
      "kind": "card",
      "cardId": "sheep_hide_r",
      "registryId": "sheep_hide_r",
      "name": "Шкура барана",
      "deck": "base",
      "art": "generated-frame-highres-text/base/base-009-style-v1-card-highres-text",
      "face": "front",
      "x": 578,
      "y": 727,
      "w": 92
    },
    {
      "page": 5,
      "uid": "c35",
      "kind": "back",
      "cardId": "back:base",
      "registryId": "back:base",
      "name": "Базовые карты",
      "deck": "base",
      "art": "backs/base-cards",
      "face": "back",
      "x": 964,
      "y": 739,
      "w": 92
    },
    {
      "page": 5,
      "uid": "c36",
      "kind": "card",
      "cardId": "sheep_ram",
      "registryId": "sheep_ram",
      "name": "Баран",
      "deck": "base",
      "art": "generated-frame-highres-text/base/base-010-style-v1-card-highres-text",
      "face": "front",
      "x": 240,
      "y": 1215,
      "w": 92
    },
    {
      "page": 5,
      "uid": "c37",
      "kind": "card",
      "cardId": "teleport_beads",
      "registryId": "teleport_beads",
      "name": "Бусы телепортации",
      "deck": "base",
      "art": "generated-frame-highres-text/base/base-003-style-v1-card-highres-text",
      "face": "front",
      "x": 957,
      "y": 1250,
      "w": 92
    },
    {
      "page": 5,
      "uid": "c38",
      "kind": "back",
      "cardId": "back:base",
      "registryId": "back:base",
      "name": "Базовые карты",
      "deck": "base",
      "art": "backs/base-cards",
      "face": "back",
      "x": 602,
      "y": 1216,
      "w": 92
    },
    {
      "page": 6,
      "uid": "c39",
      "kind": "card",
      "cardId": "griffin",
      "registryId": "griffin",
      "name": "Гриффон",
      "deck": "base",
      "art": "base/hunter/griffin-v1",
      "face": "front",
      "x": 150,
      "y": 735,
      "w": 92
    },
    {
      "page": 6,
      "uid": "c40",
      "kind": "back",
      "cardId": "back:base",
      "registryId": "back:base",
      "name": "Базовые карты",
      "deck": "base",
      "art": "backs/base-cards",
      "face": "back",
      "x": 996,
      "y": 283,
      "w": 92
    },
    {
      "page": 6,
      "uid": "c41",
      "kind": "back",
      "cardId": "back:base",
      "registryId": "back:base",
      "name": "Базовые карты",
      "deck": "base",
      "art": "backs/base-cards",
      "face": "back",
      "x": 597,
      "y": 766,
      "w": 92
    },
    {
      "page": 6,
      "uid": "c42",
      "kind": "card",
      "cardId": "teleport_beads",
      "registryId": "teleport_beads",
      "name": "Бусы телепортации",
      "deck": "base",
      "art": "generated-frame-highres-text/base/base-003-style-v1-card-highres-text",
      "face": "front",
      "x": 1004,
      "y": 773,
      "w": 92
    },
    {
      "page": 6,
      "uid": "c43",
      "kind": "back",
      "cardId": "back:base",
      "registryId": "back:base",
      "name": "Базовые карты",
      "deck": "base",
      "art": "backs/base-cards",
      "face": "back",
      "x": 985,
      "y": 1289,
      "w": 92
    },
    {
      "page": 7,
      "uid": "c44",
      "kind": "card",
      "cardId": "bp_hammer_base",
      "registryId": "bp_hammer_base",
      "name": "Чертеж на молоток",
      "deck": "base",
      "art": "generated-frame-highres-text/base/base-013-style-v1-card-highres-text",
      "face": "front",
      "x": 148,
      "y": 110,
      "w": 92
    },
    {
      "page": 7,
      "uid": "c45",
      "kind": "back",
      "cardId": "back:base",
      "registryId": "back:base",
      "name": "Базовые карты",
      "deck": "base",
      "art": "backs/base-cards",
      "face": "back",
      "x": 606,
      "y": 185,
      "w": 92
    },
    {
      "page": 7,
      "uid": "c46",
      "kind": "card",
      "cardId": "hammer",
      "registryId": "hammer",
      "name": "Молоток",
      "deck": "base",
      "art": "generated-frame-highres-text/base/base-014-style-v1-card-highres-text",
      "face": "front",
      "x": 1055,
      "y": 87,
      "w": 92
    },
    {
      "page": 7,
      "uid": "c47",
      "kind": "card",
      "cardId": "ore_medium",
      "registryId": "ore_medium",
      "name": "Грязная смешанная железная руда",
      "deck": "base",
      "art": "generated-frame-highres-text/base/base-015-style-v1-card-highres-text",
      "face": "front",
      "x": 568,
      "y": 639,
      "w": 92
    },
    {
      "page": 7,
      "uid": "c48",
      "kind": "back",
      "cardId": "back:base",
      "registryId": "back:base",
      "name": "Базовые карты",
      "deck": "base",
      "art": "backs/base-cards",
      "face": "back",
      "x": 235,
      "y": 639,
      "w": 92
    },
    {
      "page": 7,
      "uid": "c49",
      "kind": "card",
      "cardId": "teleport_beads",
      "registryId": "teleport_beads",
      "name": "Бусы телепортации",
      "deck": "base",
      "art": "generated-frame-highres-text/base/base-003-style-v1-card-highres-text",
      "face": "front",
      "x": 228,
      "y": 1116,
      "w": 92
    },
    {
      "page": 7,
      "uid": "c50",
      "kind": "back",
      "cardId": "back:base",
      "registryId": "back:base",
      "name": "Базовые карты",
      "deck": "base",
      "art": "backs/base-cards",
      "face": "back",
      "x": 955,
      "y": 699,
      "w": 92
    },
    {
      "page": 8,
      "uid": "c51",
      "kind": "back",
      "cardId": "back:mixed",
      "registryId": "back:mixed",
      "name": "Смешанный грунт",
      "deck": "mixed",
      "art": "backs/mixed-ground",
      "face": "back",
      "x": 198,
      "y": 88,
      "w": 92
    },
    {
      "page": 8,
      "uid": "c52",
      "kind": "card",
      "cardId": "art_mixed_001",
      "registryId": "art_mixed_001",
      "name": "Железная руда среднего качества",
      "deck": "mixed",
      "art": "generated-frame-highres-text/mixed/mixed-001-style-v1-card-highres-text",
      "face": "front",
      "x": 586,
      "y": 13,
      "w": 92
    },
    {
      "page": 8,
      "uid": "c53",
      "kind": "back",
      "cardId": "back:mixed",
      "registryId": "back:mixed",
      "name": "Смешанный грунт",
      "deck": "mixed",
      "art": "backs/mixed-ground",
      "face": "back",
      "x": 966,
      "y": 275,
      "w": 92
    },
    {
      "page": 8,
      "uid": "c54",
      "kind": "card",
      "cardId": "art_mixed_002",
      "registryId": "art_mixed_002",
      "name": "Грязная смешанная железная руда",
      "deck": "mixed",
      "art": "generated-frame-highres-text/mixed/mixed-002-style-v1-card-highres-text",
      "face": "front",
      "x": 112,
      "y": 675,
      "w": 92
    },
    {
      "page": 8,
      "uid": "c55",
      "kind": "card",
      "cardId": "art_mixed_001",
      "registryId": "art_mixed_001",
      "name": "Железная руда среднего качества",
      "deck": "mixed",
      "art": "generated-frame-highres-text/mixed/mixed-001-style-v1-card-highres-text",
      "face": "front",
      "x": 946,
      "y": 712,
      "w": 92
    },
    {
      "page": 8,
      "uid": "c56",
      "kind": "back",
      "cardId": "back:mixed",
      "registryId": "back:mixed",
      "name": "Смешанный грунт",
      "deck": "mixed",
      "art": "backs/mixed-ground",
      "face": "back",
      "x": 605,
      "y": 754,
      "w": 92
    },
    {
      "page": 8,
      "uid": "c57",
      "kind": "back",
      "cardId": "back:mixed",
      "registryId": "back:mixed",
      "name": "Смешанный грунт",
      "deck": "mixed",
      "art": "backs/mixed-ground",
      "face": "back",
      "x": 252,
      "y": 1260,
      "w": 92
    },
    {
      "page": 8,
      "uid": "c58",
      "kind": "card",
      "cardId": "art_mixed_001",
      "registryId": "art_mixed_001",
      "name": "Железная руда среднего качества",
      "deck": "mixed",
      "art": "generated-frame-highres-text/mixed/mixed-001-style-v1-card-highres-text",
      "face": "front",
      "x": 582,
      "y": 1250,
      "w": 92
    },
    {
      "uid": "c60",
      "kind": "back",
      "cardId": "back:mixed",
      "registryId": "back:mixed",
      "name": "Смешанный грунт",
      "deck": "mixed",
      "art": "backs/mixed-ground",
      "face": "back",
      "page": 9,
      "x": 228,
      "y": 184,
      "w": 92
    },
    {
      "uid": "c61",
      "kind": "card",
      "cardId": "art_mixed_001",
      "registryId": "art_mixed_001",
      "name": "Железная руда среднего качества",
      "deck": "mixed",
      "art": "generated-frame-highres-text/mixed/mixed-001-style-v1-card-highres-text",
      "face": "front",
      "page": 9,
      "x": 571,
      "y": 192,
      "w": 92
    },
    {
      "uid": "c62",
      "kind": "card",
      "cardId": "art_mixed_001",
      "registryId": "art_mixed_001",
      "name": "Железная руда среднего качества",
      "deck": "mixed",
      "art": "generated-frame-highres-text/mixed/mixed-001-style-v1-card-highres-text",
      "face": "front",
      "page": 9,
      "x": 222,
      "y": 644,
      "w": 92
    },
    {
      "uid": "c63",
      "kind": "back",
      "cardId": "back:mixed",
      "registryId": "back:mixed",
      "name": "Смешанный грунт",
      "deck": "mixed",
      "art": "backs/mixed-ground",
      "face": "back",
      "page": 9,
      "x": 997,
      "y": 208,
      "w": 92
    },
    {
      "uid": "c64",
      "kind": "card",
      "cardId": "art_mixed_001",
      "registryId": "art_mixed_001",
      "name": "Железная руда среднего качества",
      "deck": "mixed",
      "art": "generated-frame-highres-text/mixed/mixed-001-style-v1-card-highres-text",
      "face": "front",
      "page": 9,
      "x": 981,
      "y": 732,
      "w": 92
    },
    {
      "uid": "c65",
      "kind": "back",
      "cardId": "back:mixed",
      "registryId": "back:mixed",
      "name": "Смешанный грунт",
      "deck": "mixed",
      "art": "backs/mixed-ground",
      "face": "back",
      "page": 9,
      "x": 610,
      "y": 737,
      "w": 92
    },
    {
      "uid": "c66",
      "kind": "card",
      "cardId": "art_mixed_001",
      "registryId": "art_mixed_001",
      "name": "Железная руда среднего качества",
      "deck": "mixed",
      "art": "generated-frame-highres-text/mixed/mixed-001-style-v1-card-highres-text",
      "face": "front",
      "page": 9,
      "x": 617,
      "y": 1233,
      "w": 92
    },
    {
      "uid": "c67",
      "kind": "back",
      "cardId": "back:mixed",
      "registryId": "back:mixed",
      "name": "Смешанный грунт",
      "deck": "mixed",
      "art": "backs/mixed-ground",
      "face": "back",
      "page": 9,
      "x": 239,
      "y": 1226,
      "w": 92
    },
    {
      "uid": "c68",
      "kind": "back",
      "cardId": "back:mixed",
      "registryId": "back:mixed",
      "name": "Смешанный грунт",
      "deck": "mixed",
      "art": "backs/mixed-ground",
      "face": "back",
      "page": 9,
      "x": 964,
      "y": 1230,
      "w": 92
    },
    {
      "uid": "c69",
      "kind": "card",
      "cardId": "art_mixed_001",
      "registryId": "art_mixed_001",
      "name": "Железная руда среднего качества",
      "deck": "mixed",
      "art": "generated-frame-highres-text/mixed/mixed-001-style-v1-card-highres-text",
      "face": "front",
      "page": 10,
      "x": 189,
      "y": 172,
      "w": 92
    },
    {
      "uid": "c70",
      "kind": "back",
      "cardId": "back:mixed",
      "registryId": "back:mixed",
      "name": "Смешанный грунт",
      "deck": "mixed",
      "art": "backs/mixed-ground",
      "face": "back",
      "page": 10,
      "x": 600,
      "y": 171,
      "w": 92
    },
    {
      "uid": "c71",
      "kind": "card",
      "cardId": "art_mixed_001",
      "registryId": "art_mixed_001",
      "name": "Железная руда среднего качества",
      "deck": "mixed",
      "art": "generated-frame-highres-text/mixed/mixed-001-style-v1-card-highres-text",
      "face": "front",
      "page": 10,
      "x": 941,
      "y": 178,
      "w": 92
    },
    {
      "uid": "c72",
      "kind": "card",
      "cardId": "art_mixed_001",
      "registryId": "art_mixed_001",
      "name": "Железная руда среднего качества",
      "deck": "mixed",
      "art": "generated-frame-highres-text/mixed/mixed-001-style-v1-card-highres-text",
      "face": "front",
      "page": 10,
      "x": 593,
      "y": 662,
      "w": 92
    },
    {
      "uid": "c73",
      "kind": "back",
      "cardId": "back:mixed",
      "registryId": "back:mixed",
      "name": "Смешанный грунт",
      "deck": "mixed",
      "art": "backs/mixed-ground",
      "face": "back",
      "page": 10,
      "x": 252,
      "y": 664,
      "w": 92
    },
    {
      "uid": "c74",
      "kind": "card",
      "cardId": "art_mixed_001",
      "registryId": "art_mixed_001",
      "name": "Железная руда среднего качества",
      "deck": "mixed",
      "art": "generated-frame-highres-text/mixed/mixed-001-style-v1-card-highres-text",
      "face": "front",
      "page": 10,
      "x": 238,
      "y": 1216,
      "w": 92
    },
    {
      "uid": "c75",
      "kind": "back",
      "cardId": "back:mixed",
      "registryId": "back:mixed",
      "name": "Смешанный грунт",
      "deck": "mixed",
      "art": "backs/mixed-ground",
      "face": "back",
      "page": 10,
      "x": 984,
      "y": 685,
      "w": 92
    },
    {
      "uid": "c76",
      "kind": "card",
      "cardId": "art_mixed_001",
      "registryId": "art_mixed_001",
      "name": "Железная руда среднего качества",
      "deck": "mixed",
      "art": "generated-frame-highres-text/mixed/mixed-001-style-v1-card-highres-text",
      "face": "front",
      "page": 10,
      "x": 984,
      "y": 1168,
      "w": 92
    },
    {
      "uid": "c77",
      "kind": "back",
      "cardId": "back:mixed",
      "registryId": "back:mixed",
      "name": "Смешанный грунт",
      "deck": "mixed",
      "art": "backs/mixed-ground",
      "face": "back",
      "page": 10,
      "x": 632,
      "y": 1164,
      "w": 92
    },
    {
      "uid": "c78",
      "kind": "card",
      "cardId": "art_mixed_001",
      "registryId": "art_mixed_001",
      "name": "Железная руда среднего качества",
      "deck": "mixed",
      "art": "generated-frame-highres-text/mixed/mixed-001-style-v1-card-highres-text",
      "face": "front",
      "page": 11,
      "x": 568,
      "y": 198,
      "w": 92
    },
    {
      "uid": "c79",
      "kind": "back",
      "cardId": "back:mixed",
      "registryId": "back:mixed",
      "name": "Смешанный грунт",
      "deck": "mixed",
      "art": "backs/mixed-ground",
      "face": "back",
      "page": 11,
      "x": 228,
      "y": 198,
      "w": 92
    },
    {
      "uid": "c80",
      "kind": "back",
      "cardId": "back:mixed",
      "registryId": "back:mixed",
      "name": "Смешанный грунт",
      "deck": "mixed",
      "art": "backs/mixed-ground",
      "face": "back",
      "page": 11,
      "x": 987,
      "y": 205,
      "w": 92
    },
    {
      "uid": "c81",
      "kind": "card",
      "cardId": "art_mixed_002",
      "registryId": "art_mixed_002",
      "name": "Грязная смешанная железная руда",
      "deck": "mixed",
      "art": "generated-frame-highres-text/mixed/mixed-002-style-v1-card-highres-text",
      "face": "front",
      "page": 11,
      "x": 96,
      "y": 662,
      "w": 92
    },
    {
      "uid": "c82",
      "kind": "card",
      "cardId": "art_mixed_002",
      "registryId": "art_mixed_002",
      "name": "Грязная смешанная железная руда",
      "deck": "mixed",
      "art": "generated-frame-highres-text/mixed/mixed-002-style-v1-card-highres-text",
      "face": "front",
      "page": 11,
      "x": 1002,
      "y": 662,
      "w": 92
    },
    {
      "uid": "c83",
      "kind": "back",
      "cardId": "back:mixed",
      "registryId": "back:mixed",
      "name": "Смешанный грунт",
      "deck": "mixed",
      "art": "backs/mixed-ground",
      "face": "back",
      "page": 11,
      "x": 623,
      "y": 701,
      "w": 92
    },
    {
      "uid": "c84",
      "kind": "card",
      "cardId": "art_mixed_002",
      "registryId": "art_mixed_002",
      "name": "Грязная смешанная железная руда",
      "deck": "mixed",
      "art": "generated-frame-highres-text/mixed/mixed-002-style-v1-card-highres-text",
      "face": "front",
      "page": 11,
      "x": 633,
      "y": 1146,
      "w": 92
    },
    {
      "uid": "c85",
      "kind": "back",
      "cardId": "back:mixed",
      "registryId": "back:mixed",
      "name": "Смешанный грунт",
      "deck": "mixed",
      "art": "backs/mixed-ground",
      "face": "back",
      "page": 11,
      "x": 246,
      "y": 1174,
      "w": 92
    },
    {
      "uid": "c86",
      "kind": "back",
      "cardId": "back:mixed",
      "registryId": "back:mixed",
      "name": "Смешанный грунт",
      "deck": "mixed",
      "art": "backs/mixed-ground",
      "face": "back",
      "page": 11,
      "x": 957,
      "y": 1200,
      "w": 92
    },
    {
      "uid": "c87",
      "kind": "card",
      "cardId": "art_mixed_002",
      "registryId": "art_mixed_002",
      "name": "Грязная смешанная железная руда",
      "deck": "mixed",
      "art": "generated-frame-highres-text/mixed/mixed-002-style-v1-card-highres-text",
      "face": "front",
      "page": 12,
      "x": 258,
      "y": 184,
      "w": 92
    },
    {
      "uid": "c88",
      "kind": "back",
      "cardId": "back:mixed",
      "registryId": "back:mixed",
      "name": "Смешанный грунт",
      "deck": "mixed",
      "art": "backs/mixed-ground",
      "face": "back",
      "page": 12,
      "x": 648,
      "y": 180,
      "w": 92
    },
    {
      "uid": "c89",
      "kind": "card",
      "cardId": "art_mixed_002",
      "registryId": "art_mixed_002",
      "name": "Грязная смешанная железная руда",
      "deck": "mixed",
      "art": "generated-frame-highres-text/mixed/mixed-002-style-v1-card-highres-text",
      "face": "front",
      "page": 12,
      "x": 1022,
      "y": 192,
      "w": 92
    },
    {
      "uid": "c90",
      "kind": "card",
      "cardId": "art_mixed_002",
      "registryId": "art_mixed_002",
      "name": "Грязная смешанная железная руда",
      "deck": "mixed",
      "art": "generated-frame-highres-text/mixed/mixed-002-style-v1-card-highres-text",
      "face": "front",
      "page": 12,
      "x": 617,
      "y": 669,
      "w": 92
    },
    {
      "uid": "c91",
      "kind": "back",
      "cardId": "back:mixed",
      "registryId": "back:mixed",
      "name": "Смешанный грунт",
      "deck": "mixed",
      "art": "backs/mixed-ground",
      "face": "back",
      "page": 12,
      "x": 243,
      "y": 703,
      "w": 92
    },
    {
      "uid": "c92",
      "kind": "card",
      "cardId": "art_mixed_002",
      "registryId": "art_mixed_002",
      "name": "Грязная смешанная железная руда",
      "deck": "mixed",
      "art": "generated-frame-highres-text/mixed/mixed-002-style-v1-card-highres-text",
      "face": "front",
      "page": 12,
      "x": 283,
      "y": 1190,
      "w": 92
    },
    {
      "uid": "c93",
      "kind": "back",
      "cardId": "back:mixed",
      "registryId": "back:mixed",
      "name": "Смешанный грунт",
      "deck": "mixed",
      "art": "backs/mixed-ground",
      "face": "back",
      "page": 12,
      "x": 1019,
      "y": 725,
      "w": 92
    },
    {
      "uid": "c94",
      "kind": "card",
      "cardId": "art_mixed_002",
      "registryId": "art_mixed_002",
      "name": "Грязная смешанная железная руда",
      "deck": "mixed",
      "art": "generated-frame-highres-text/mixed/mixed-002-style-v1-card-highres-text",
      "face": "front",
      "page": 12,
      "x": 1007,
      "y": 1206,
      "w": 92
    },
    {
      "uid": "c95",
      "kind": "back",
      "cardId": "back:mixed",
      "registryId": "back:mixed",
      "name": "Смешанный грунт",
      "deck": "mixed",
      "art": "backs/mixed-ground",
      "face": "back",
      "page": 12,
      "x": 625,
      "y": 1209,
      "w": 92
    },
    {
      "uid": "c96",
      "kind": "card",
      "cardId": "art_mixed_002",
      "registryId": "art_mixed_002",
      "name": "Грязная смешанная железная руда",
      "deck": "mixed",
      "art": "generated-frame-highres-text/mixed/mixed-002-style-v1-card-highres-text",
      "face": "front",
      "page": 13,
      "x": 634,
      "y": 161,
      "w": 92
    },
    {
      "uid": "c97",
      "kind": "back",
      "cardId": "back:mixed",
      "registryId": "back:mixed",
      "name": "Смешанный грунт",
      "deck": "mixed",
      "art": "backs/mixed-ground",
      "face": "back",
      "page": 13,
      "x": 237,
      "y": 207,
      "w": 92
    },
    {
      "uid": "c98",
      "kind": "back",
      "cardId": "back:mixed",
      "registryId": "back:mixed",
      "name": "Смешанный грунт",
      "deck": "mixed",
      "art": "backs/mixed-ground",
      "face": "back",
      "page": 13,
      "x": 1021,
      "y": 205,
      "w": 92
    },
    {
      "uid": "c99",
      "kind": "card",
      "cardId": "art_mixed_002",
      "registryId": "art_mixed_002",
      "name": "Грязная смешанная железная руда",
      "deck": "mixed",
      "art": "generated-frame-highres-text/mixed/mixed-002-style-v1-card-highres-text",
      "face": "front",
      "page": 13,
      "x": 295,
      "y": 650,
      "w": 92
    },
    {
      "uid": "c100",
      "kind": "back",
      "cardId": "back:mixed",
      "registryId": "back:mixed",
      "name": "Смешанный грунт",
      "deck": "mixed",
      "art": "backs/mixed-ground",
      "face": "back",
      "page": 13,
      "x": 646,
      "y": 730,
      "w": 92
    },
    {
      "uid": "c101",
      "kind": "card",
      "cardId": "art_mixed_002",
      "registryId": "art_mixed_002",
      "name": "Грязная смешанная железная руда",
      "deck": "mixed",
      "art": "generated-frame-highres-text/mixed/mixed-002-style-v1-card-highres-text",
      "face": "front",
      "page": 13,
      "x": 1023,
      "y": 710,
      "w": 92
    },
    {
      "uid": "c102",
      "kind": "back",
      "cardId": "back:mixed",
      "registryId": "back:mixed",
      "name": "Смешанный грунт",
      "deck": "mixed",
      "art": "backs/mixed-ground",
      "face": "back",
      "page": 13,
      "x": 253,
      "y": 1209,
      "w": 92
    },
    {
      "uid": "c103",
      "kind": "card",
      "cardId": "art_mixed_002",
      "registryId": "art_mixed_002",
      "name": "Грязная смешанная железная руда",
      "deck": "mixed",
      "art": "generated-frame-highres-text/mixed/mixed-002-style-v1-card-highres-text",
      "face": "front",
      "page": 13,
      "x": 624,
      "y": 1221,
      "w": 92
    },
    {
      "uid": "c104",
      "kind": "back",
      "cardId": "back:mixed",
      "registryId": "back:mixed",
      "name": "Смешанный грунт",
      "deck": "mixed",
      "art": "backs/mixed-ground",
      "face": "back",
      "page": 13,
      "x": 1041,
      "y": 1227,
      "w": 92
    },
    {
      "uid": "c105",
      "kind": "card",
      "cardId": "art_mixed_002",
      "registryId": "art_mixed_002",
      "name": "Грязная смешанная железная руда",
      "deck": "mixed",
      "art": "generated-frame-highres-text/mixed/mixed-002-style-v1-card-highres-text",
      "face": "front",
      "page": 14,
      "x": 247,
      "y": 151,
      "w": 92
    },
    {
      "uid": "c106",
      "kind": "back",
      "cardId": "back:mixed",
      "registryId": "back:mixed",
      "name": "Смешанный грунт",
      "deck": "mixed",
      "art": "backs/mixed-ground",
      "face": "back",
      "page": 14,
      "x": 618,
      "y": 130,
      "w": 92
    },
    {
      "uid": "c107",
      "kind": "card",
      "cardId": "art_mixed_003",
      "registryId": "art_mixed_003",
      "name": "Сухой череп",
      "deck": "mixed",
      "art": "generated-frame-highres-text/mixed/mixed-003-style-v1-card-highres-text",
      "face": "front",
      "page": 14,
      "x": 947,
      "y": 73,
      "w": 92
    },
    {
      "uid": "c108",
      "kind": "card",
      "cardId": "art_mixed_003",
      "registryId": "art_mixed_003",
      "name": "Сухой череп",
      "deck": "mixed",
      "art": "generated-frame-highres-text/mixed/mixed-003-style-v1-card-highres-text",
      "face": "front",
      "page": 14,
      "x": 564,
      "y": 636,
      "w": 92
    },
    {
      "uid": "c109",
      "kind": "back",
      "cardId": "back:mixed",
      "registryId": "back:mixed",
      "name": "Смешанный грунт",
      "deck": "mixed",
      "art": "backs/mixed-ground",
      "face": "back",
      "page": 14,
      "x": 234,
      "y": 701,
      "w": 92
    },
    {
      "uid": "c110",
      "kind": "card",
      "cardId": "art_mixed_003",
      "registryId": "art_mixed_003",
      "name": "Сухой череп",
      "deck": "mixed",
      "art": "generated-frame-highres-text/mixed/mixed-003-style-v1-card-highres-text",
      "face": "front",
      "page": 14,
      "x": 257,
      "y": 1146,
      "w": 92
    },
    {
      "uid": "c111",
      "kind": "back",
      "cardId": "back:mixed",
      "registryId": "back:mixed",
      "name": "Смешанный грунт",
      "deck": "mixed",
      "art": "backs/mixed-ground",
      "face": "back",
      "page": 14,
      "x": 1029,
      "y": 679,
      "w": 92
    },
    {
      "uid": "c112",
      "kind": "card",
      "cardId": "hide_red",
      "registryId": "hide_red",
      "name": "Очищенная шкура зверя",
      "deck": "mixed",
      "art": "generated-frame-highres-text/mixed/mixed-004-style-v1-card-highres-text",
      "face": "front",
      "page": 14,
      "x": 965,
      "y": 1121,
      "w": 92
    },
    {
      "uid": "c113",
      "kind": "back",
      "cardId": "back:mixed",
      "registryId": "back:mixed",
      "name": "Смешанный грунт",
      "deck": "mixed",
      "art": "backs/mixed-ground",
      "face": "back",
      "page": 14,
      "x": 627,
      "y": 1201,
      "w": 92
    },
    {
      "uid": "c114",
      "kind": "back",
      "cardId": "back:base",
      "registryId": "back:base",
      "name": "Базовые карты",
      "deck": "base",
      "art": "backs/base-cards",
      "face": "back",
      "page": 15,
      "x": 242,
      "y": 213,
      "w": 92
    },
    {
      "uid": "c115",
      "kind": "card",
      "cardId": "art_mixed_005",
      "registryId": "art_mixed_005",
      "name": "Шкура убитого зверя",
      "deck": "mixed",
      "art": "generated-frame-highres-text/mixed/mixed-005-style-v1-card-highres-text",
      "face": "front",
      "page": 15,
      "x": 638,
      "y": 141,
      "w": 92
    },
    {
      "uid": "c116",
      "kind": "back",
      "cardId": "back:base",
      "registryId": "back:base",
      "name": "Базовые карты",
      "deck": "base",
      "art": "backs/base-cards",
      "face": "back",
      "page": 15,
      "x": 993,
      "y": 218,
      "w": 92
    },
    {
      "uid": "c117",
      "kind": "card",
      "cardId": "art_mixed_006",
      "registryId": "art_mixed_006",
      "name": "Дикий кабан",
      "deck": "mixed",
      "art": "generated-frame-highres-text/mixed/mixed-006-style-v1-card-highres-text",
      "face": "front",
      "page": 15,
      "x": 253,
      "y": 598,
      "w": 92
    },
    {
      "uid": "c118",
      "kind": "back",
      "cardId": "back:mixed",
      "registryId": "back:mixed",
      "name": "Смешанный грунт",
      "deck": "mixed",
      "art": "backs/mixed-ground",
      "face": "back",
      "page": 15,
      "x": 607,
      "y": 682,
      "w": 92
    },
    {
      "uid": "c119",
      "kind": "card",
      "cardId": "hide_red",
      "registryId": "hide_red",
      "name": "Очищенная шкура зверя",
      "deck": "mixed",
      "art": "generated-frame-highres-text/mixed/mixed-004-style-v1-card-highres-text",
      "face": "front",
      "page": 15,
      "x": 1009,
      "y": 692,
      "w": 92
    },
    {
      "uid": "c120",
      "kind": "back",
      "cardId": "back:base",
      "registryId": "back:base",
      "name": "Базовые карты",
      "deck": "base",
      "art": "backs/base-cards",
      "face": "back",
      "page": 15,
      "x": 177,
      "y": 1136,
      "w": 92
    },
    {
      "uid": "c121",
      "kind": "card",
      "cardId": "art_mixed_005",
      "registryId": "art_mixed_005",
      "name": "Шкура убитого зверя",
      "deck": "mixed",
      "art": "generated-frame-highres-text/mixed/mixed-005-style-v1-card-highres-text",
      "face": "front",
      "page": 15,
      "x": 644,
      "y": 1129,
      "w": 92
    },
    {
      "uid": "c122",
      "kind": "back",
      "cardId": "back:base",
      "registryId": "back:base",
      "name": "Базовые карты",
      "deck": "base",
      "art": "backs/base-cards",
      "face": "back",
      "page": 15,
      "x": 1026,
      "y": 1177,
      "w": 92
    },
    {
      "uid": "c123",
      "kind": "card",
      "cardId": "art_mixed_006",
      "registryId": "art_mixed_006",
      "name": "Дикий кабан",
      "deck": "mixed",
      "art": "generated-frame-highres-text/mixed/mixed-006-style-v1-card-highres-text",
      "face": "front",
      "page": 16,
      "x": 234,
      "y": 169,
      "w": 92
    },
    {
      "uid": "c124",
      "kind": "card",
      "cardId": "hide_red",
      "registryId": "hide_red",
      "name": "Очищенная шкура зверя",
      "deck": "mixed",
      "art": "generated-frame-highres-text/mixed/mixed-004-style-v1-card-highres-text",
      "face": "front",
      "page": 16,
      "x": 1036,
      "y": 192,
      "w": 92
    },
    {
      "uid": "c125",
      "kind": "back",
      "cardId": "back:mixed",
      "registryId": "back:mixed",
      "name": "Смешанный грунт",
      "deck": "mixed",
      "art": "backs/mixed-ground",
      "face": "back",
      "page": 16,
      "x": 634,
      "y": 202,
      "w": 92
    },
    {
      "uid": "c126",
      "kind": "back",
      "cardId": "back:base",
      "registryId": "back:base",
      "name": "Базовые карты",
      "deck": "base",
      "art": "backs/base-cards",
      "face": "back",
      "page": 16,
      "x": 246,
      "y": 750,
      "w": 92
    },
    {
      "uid": "c127",
      "kind": "card",
      "cardId": "art_mixed_005",
      "registryId": "art_mixed_005",
      "name": "Шкура убитого зверя",
      "deck": "mixed",
      "art": "generated-frame-highres-text/mixed/mixed-005-style-v1-card-highres-text",
      "face": "front",
      "page": 16,
      "x": 630,
      "y": 702,
      "w": 92
    },
    {
      "uid": "c128",
      "kind": "back",
      "cardId": "back:base",
      "registryId": "back:base",
      "name": "Базовые карты",
      "deck": "base",
      "art": "backs/base-cards",
      "face": "back",
      "page": 16,
      "x": 1009,
      "y": 763,
      "w": 92
    },
    {
      "uid": "c129",
      "kind": "card",
      "cardId": "art_mixed_006",
      "registryId": "art_mixed_006",
      "name": "Дикий кабан",
      "deck": "mixed",
      "art": "generated-frame-highres-text/mixed/mixed-006-style-v1-card-highres-text",
      "face": "front",
      "page": 16,
      "x": 247,
      "y": 1189,
      "w": 92
    },
    {
      "uid": "c130",
      "kind": "back",
      "cardId": "back:mixed",
      "registryId": "back:mixed",
      "name": "Смешанный грунт",
      "deck": "mixed",
      "art": "backs/mixed-ground",
      "face": "back",
      "page": 16,
      "x": 613,
      "y": 1266,
      "w": 92
    },
    {
      "uid": "c131",
      "kind": "card",
      "cardId": "hide_red",
      "registryId": "hide_red",
      "name": "Очищенная шкура зверя",
      "deck": "mixed",
      "art": "generated-frame-highres-text/mixed/mixed-004-style-v1-card-highres-text",
      "face": "front",
      "page": 16,
      "x": 962,
      "y": 1154,
      "w": 92
    },
    {
      "uid": "c132",
      "kind": "back",
      "cardId": "back:base",
      "registryId": "back:base",
      "name": "Базовые карты",
      "deck": "base",
      "art": "backs/base-cards",
      "face": "back",
      "page": 17,
      "x": 228,
      "y": 181,
      "w": 92
    },
    {
      "uid": "c133",
      "kind": "card",
      "cardId": "art_mixed_005",
      "registryId": "art_mixed_005",
      "name": "Шкура убитого зверя",
      "deck": "mixed",
      "art": "generated-frame-highres-text/mixed/mixed-005-style-v1-card-highres-text",
      "face": "front",
      "page": 17,
      "x": 588,
      "y": 137,
      "w": 92
    },
    {
      "uid": "c134",
      "kind": "back",
      "cardId": "back:base",
      "registryId": "back:base",
      "name": "Базовые карты",
      "deck": "base",
      "art": "backs/base-cards",
      "face": "back",
      "page": 17,
      "x": 934,
      "y": 213,
      "w": 92
    },
    {
      "uid": "c135",
      "kind": "card",
      "cardId": "art_mixed_006",
      "registryId": "art_mixed_006",
      "name": "Дикий кабан",
      "deck": "mixed",
      "art": "generated-frame-highres-text/mixed/mixed-006-style-v1-card-highres-text",
      "face": "front",
      "page": 17,
      "x": 264,
      "y": 663,
      "w": 92
    },
    {
      "uid": "c136",
      "kind": "back",
      "cardId": "back:mixed",
      "registryId": "back:mixed",
      "name": "Смешанный грунт",
      "deck": "mixed",
      "art": "backs/mixed-ground",
      "face": "back",
      "page": 17,
      "x": 650,
      "y": 690,
      "w": 92
    },
    {
      "uid": "c137",
      "kind": "card",
      "cardId": "hide_red",
      "registryId": "hide_red",
      "name": "Очищенная шкура зверя",
      "deck": "mixed",
      "art": "generated-frame-highres-text/mixed/mixed-004-style-v1-card-highres-text",
      "face": "front",
      "page": 17,
      "x": 990,
      "y": 630,
      "w": 92
    },
    {
      "uid": "c138",
      "kind": "back",
      "cardId": "back:base",
      "registryId": "back:base",
      "name": "Базовые карты",
      "deck": "base",
      "art": "backs/base-cards",
      "face": "back",
      "page": 17,
      "x": 209,
      "y": 1157,
      "w": 92
    },
    {
      "uid": "c139",
      "kind": "card",
      "cardId": "art_mixed_005",
      "registryId": "art_mixed_005",
      "name": "Шкура убитого зверя",
      "deck": "mixed",
      "art": "generated-frame-highres-text/mixed/mixed-005-style-v1-card-highres-text",
      "face": "front",
      "page": 17,
      "x": 626,
      "y": 1180,
      "w": 92
    },
    {
      "uid": "c140",
      "kind": "back",
      "cardId": "back:base",
      "registryId": "back:base",
      "name": "Базовые карты",
      "deck": "base",
      "art": "backs/base-cards",
      "face": "back",
      "page": 17,
      "x": 996,
      "y": 1186,
      "w": 92
    },
    {
      "uid": "c141",
      "kind": "card",
      "cardId": "art_mixed_006",
      "registryId": "art_mixed_006",
      "name": "Дикий кабан",
      "deck": "mixed",
      "art": "generated-frame-highres-text/mixed/mixed-006-style-v1-card-highres-text",
      "face": "front",
      "page": 18,
      "x": 230,
      "y": 126,
      "w": 92
    },
    {
      "uid": "c142",
      "kind": "back",
      "cardId": "back:mixed",
      "registryId": "back:mixed",
      "name": "Смешанный грунт",
      "deck": "mixed",
      "art": "backs/mixed-ground",
      "face": "back",
      "page": 18,
      "x": 587,
      "y": 176,
      "w": 92
    },
    {
      "uid": "c143",
      "kind": "card",
      "cardId": "hide_red",
      "registryId": "hide_red",
      "name": "Очищенная шкура зверя",
      "deck": "mixed",
      "art": "generated-frame-highres-text/mixed/mixed-004-style-v1-card-highres-text",
      "face": "front",
      "page": 18,
      "x": 1026,
      "y": 108,
      "w": 92
    },
    {
      "uid": "c144",
      "kind": "back",
      "cardId": "back:base",
      "registryId": "back:base",
      "name": "Базовые карты",
      "deck": "base",
      "art": "backs/base-cards",
      "face": "back",
      "page": 18,
      "x": 216,
      "y": 762,
      "w": 92
    },
    {
      "uid": "c145",
      "kind": "card",
      "cardId": "art_mixed_005",
      "registryId": "art_mixed_005",
      "name": "Шкура убитого зверя",
      "deck": "mixed",
      "art": "generated-frame-highres-text/mixed/mixed-005-style-v1-card-highres-text",
      "face": "front",
      "page": 18,
      "x": 627,
      "y": 731,
      "w": 92
    },
    {
      "uid": "c146",
      "kind": "back",
      "cardId": "back:base",
      "registryId": "back:base",
      "name": "Базовые карты",
      "deck": "base",
      "art": "backs/base-cards",
      "face": "back",
      "page": 18,
      "x": 968,
      "y": 769,
      "w": 92
    },
    {
      "uid": "c147",
      "kind": "card",
      "cardId": "art_mixed_006",
      "registryId": "art_mixed_006",
      "name": "Дикий кабан",
      "deck": "mixed",
      "art": "generated-frame-highres-text/mixed/mixed-006-style-v1-card-highres-text",
      "face": "front",
      "page": 18,
      "x": 241,
      "y": 1164,
      "w": 92
    },
    {
      "uid": "c148",
      "kind": "back",
      "cardId": "back:mixed",
      "registryId": "back:mixed",
      "name": "Смешанный грунт",
      "deck": "mixed",
      "art": "backs/mixed-ground",
      "face": "back",
      "page": 18,
      "x": 637,
      "y": 1247,
      "w": 92
    },
    {
      "uid": "c149",
      "kind": "card",
      "cardId": "gold_nugget",
      "registryId": "gold_nugget",
      "name": "Малый золотой самородок",
      "deck": "mixed",
      "art": "generated-frame-highres-text/mixed/mixed-007-style-v1-card-highres-text",
      "face": "front",
      "page": 18,
      "x": 987,
      "y": 1166,
      "w": 92
    },
    {
      "uid": "c150",
      "kind": "back",
      "cardId": "back:mixed",
      "registryId": "back:mixed",
      "name": "Смешанный грунт",
      "deck": "mixed",
      "art": "backs/mixed-ground",
      "face": "back",
      "page": 19,
      "x": 217,
      "y": 186,
      "w": 92
    },
    {
      "uid": "c151",
      "kind": "card",
      "cardId": "gold_nugget",
      "registryId": "gold_nugget",
      "name": "Малый золотой самородок",
      "deck": "mixed",
      "art": "generated-frame-highres-text/mixed/mixed-007-style-v1-card-highres-text",
      "face": "front",
      "page": 19,
      "x": 618,
      "y": 125,
      "w": 92
    },
    {
      "uid": "c152",
      "kind": "card",
      "cardId": "gold_nugget",
      "registryId": "gold_nugget",
      "name": "Малый золотой самородок",
      "deck": "mixed",
      "art": "generated-frame-highres-text/mixed/mixed-007-style-v1-card-highres-text",
      "face": "front",
      "page": 19,
      "x": 240,
      "y": 625,
      "w": 92
    },
    {
      "uid": "c153",
      "kind": "back",
      "cardId": "back:mixed",
      "registryId": "back:mixed",
      "name": "Смешанный грунт",
      "deck": "mixed",
      "art": "backs/mixed-ground",
      "face": "back",
      "page": 19,
      "x": 1021,
      "y": 186,
      "w": 92
    },
    {
      "uid": "c154",
      "kind": "card",
      "cardId": "gold_nugget",
      "registryId": "gold_nugget",
      "name": "Малый золотой самородок",
      "deck": "mixed",
      "art": "generated-frame-highres-text/mixed/mixed-007-style-v1-card-highres-text",
      "face": "front",
      "page": 19,
      "x": 1015,
      "y": 617,
      "w": 92
    },
    {
      "uid": "c155",
      "kind": "back",
      "cardId": "back:mixed",
      "registryId": "back:mixed",
      "name": "Смешанный грунт",
      "deck": "mixed",
      "art": "backs/mixed-ground",
      "face": "back",
      "page": 19,
      "x": 568,
      "y": 697,
      "w": 92
    },
    {
      "uid": "c156",
      "kind": "card",
      "cardId": "gold_nugget",
      "registryId": "gold_nugget",
      "name": "Малый золотой самородок",
      "deck": "mixed",
      "art": "generated-frame-highres-text/mixed/mixed-007-style-v1-card-highres-text",
      "face": "front",
      "page": 19,
      "x": 608,
      "y": 1107,
      "w": 92
    },
    {
      "uid": "c157",
      "kind": "back",
      "cardId": "back:mixed",
      "registryId": "back:mixed",
      "name": "Смешанный грунт",
      "deck": "mixed",
      "art": "backs/mixed-ground",
      "face": "back",
      "page": 19,
      "x": 232,
      "y": 1176,
      "w": 92
    },
    {
      "uid": "c158",
      "kind": "back",
      "cardId": "back:mixed",
      "registryId": "back:mixed",
      "name": "Смешанный грунт",
      "deck": "mixed",
      "art": "backs/mixed-ground",
      "face": "back",
      "page": 19,
      "x": 974,
      "y": 1183,
      "w": 92
    }
  ],
  "links": [
    {
      "uid": "l1",
      "from": "c2",
      "to": "c1"
    },
    {
      "uid": "l2",
      "from": "c4",
      "to": "c3"
    },
    {
      "uid": "l3",
      "from": "c6",
      "to": "c5"
    },
    {
      "uid": "l4",
      "from": "c7",
      "to": "c8"
    },
    {
      "uid": "l5",
      "from": "c10",
      "to": "c9"
    },
    {
      "uid": "l6",
      "from": "c12",
      "to": "c11"
    },
    {
      "uid": "l7",
      "from": "c13",
      "to": "c14"
    },
    {
      "uid": "l8",
      "from": "c16",
      "to": "c15"
    },
    {
      "uid": "l9",
      "from": "c18",
      "to": "c17"
    },
    {
      "uid": "l10",
      "from": "c20",
      "to": "c19"
    },
    {
      "uid": "l11",
      "from": "c22",
      "to": "c21"
    },
    {
      "uid": "l12",
      "from": "c24",
      "to": "c23"
    },
    {
      "uid": "l13",
      "from": "c26",
      "to": "c25"
    },
    {
      "uid": "l14",
      "from": "c27",
      "to": "c28"
    },
    {
      "uid": "l15",
      "from": "c29",
      "to": "c30"
    },
    {
      "uid": "l16",
      "from": "c32",
      "to": "c31"
    },
    {
      "uid": "l17",
      "from": "c34",
      "to": "c33"
    },
    {
      "uid": "l18",
      "from": "c36",
      "to": "c35"
    },
    {
      "uid": "l19",
      "from": "c38",
      "to": "c37"
    },
    {
      "uid": "l20",
      "from": "c40",
      "to": "c39"
    },
    {
      "uid": "l21",
      "from": "c42",
      "to": "c41"
    },
    {
      "uid": "l22",
      "from": "c43",
      "to": "c44"
    },
    {
      "uid": "l23",
      "from": "c46",
      "to": "c45"
    },
    {
      "uid": "l24",
      "from": "c48",
      "to": "c47"
    },
    {
      "uid": "l25",
      "from": "c50",
      "to": "c49"
    },
    {
      "uid": "l26",
      "from": "c52",
      "to": "c51"
    },
    {
      "uid": "l27",
      "from": "c54",
      "to": "c53"
    },
    {
      "uid": "l28",
      "from": "c56",
      "to": "c55"
    },
    {
      "uid": "l29",
      "from": "c57",
      "to": "c58"
    },
    {
      "uid": "l30",
      "from": "c61",
      "to": "c60"
    },
    {
      "uid": "l31",
      "from": "c62",
      "to": "c63"
    },
    {
      "uid": "l32",
      "from": "c64",
      "to": "c65"
    },
    {
      "uid": "l33",
      "from": "c66",
      "to": "c67"
    },
    {
      "uid": "l34",
      "from": "c68",
      "to": "c69"
    },
    {
      "uid": "l35",
      "from": "c71",
      "to": "c70"
    },
    {
      "uid": "l36",
      "from": "c72",
      "to": "c73"
    },
    {
      "uid": "l37",
      "from": "c74",
      "to": "c75"
    },
    {
      "uid": "l38",
      "from": "c76",
      "to": "c77"
    },
    {
      "uid": "l39",
      "from": "c79",
      "to": "c78"
    },
    {
      "uid": "l40",
      "from": "c81",
      "to": "c80"
    },
    {
      "uid": "l41",
      "from": "c82",
      "to": "c83"
    },
    {
      "uid": "l42",
      "from": "c84",
      "to": "c85"
    },
    {
      "uid": "l43",
      "from": "c86",
      "to": "c87"
    },
    {
      "uid": "l44",
      "from": "c89",
      "to": "c88"
    },
    {
      "uid": "l45",
      "from": "c90",
      "to": "c91"
    },
    {
      "uid": "l46",
      "from": "c92",
      "to": "c93"
    },
    {
      "uid": "l47",
      "from": "c94",
      "to": "c95"
    },
    {
      "uid": "l48",
      "from": "c97",
      "to": "c96"
    },
    {
      "uid": "l49",
      "from": "c98",
      "to": "c99"
    },
    {
      "uid": "l50",
      "from": "c100",
      "to": "c101"
    },
    {
      "uid": "l51",
      "from": "c102",
      "to": "c103"
    },
    {
      "uid": "l52",
      "from": "c104",
      "to": "c105"
    },
    {
      "uid": "l53",
      "from": "c107",
      "to": "c106"
    },
    {
      "uid": "l54",
      "from": "c108",
      "to": "c109"
    },
    {
      "uid": "l55",
      "from": "c110",
      "to": "c111"
    },
    {
      "uid": "l56",
      "from": "c113",
      "to": "c112"
    },
    {
      "uid": "l57",
      "from": "c114",
      "to": "c115"
    },
    {
      "uid": "l58",
      "from": "c117",
      "to": "c116"
    },
    {
      "uid": "l59",
      "from": "c119",
      "to": "c118"
    },
    {
      "uid": "l60",
      "from": "c120",
      "to": "c121"
    },
    {
      "uid": "l61",
      "from": "c122",
      "to": "c123"
    },
    {
      "uid": "l62",
      "from": "c125",
      "to": "c124"
    },
    {
      "uid": "l63",
      "from": "c127",
      "to": "c126"
    },
    {
      "uid": "l64",
      "from": "c129",
      "to": "c128"
    },
    {
      "uid": "l65",
      "from": "c131",
      "to": "c130"
    },
    {
      "uid": "l66",
      "from": "c133",
      "to": "c132"
    },
    {
      "uid": "l67",
      "from": "c135",
      "to": "c134"
    },
    {
      "uid": "l68",
      "from": "c137",
      "to": "c136"
    },
    {
      "uid": "l69",
      "from": "c139",
      "to": "c138"
    },
    {
      "uid": "l70",
      "from": "c140",
      "to": "c141"
    },
    {
      "uid": "l71",
      "from": "c143",
      "to": "c142"
    },
    {
      "uid": "l72",
      "from": "c145",
      "to": "c144"
    },
    {
      "uid": "l73",
      "from": "c147",
      "to": "c146"
    },
    {
      "uid": "l74",
      "from": "c149",
      "to": "c148"
    },
    {
      "uid": "l75",
      "from": "c151",
      "to": "c150"
    },
    {
      "uid": "l76",
      "from": "c152",
      "to": "c153"
    },
    {
      "uid": "l77",
      "from": "c154",
      "to": "c155"
    },
    {
      "uid": "l78",
      "from": "c156",
      "to": "c157"
    }
  ],
  "textBoxes": [
    {
      "page": 1,
      "text": "Чертёж на дубину.\nНеобходимые материалы для\nизготовления предмета: убейти\nкабана, медведя или волка. То\nчто вы заберёте с убитого зверя\nотдайте шаману. После этого воин\nоткроет чертёж и забирет дубину.",
      "cardUid": null,
      "cardKey": "bp_club_base",
      "uid": "t2",
      "x": 104,
      "y": 953,
      "w": 360,
      "h": 217
    },
    {
      "page": 1,
      "text": "Дубина \nКласс:воин\nАтака по врагу: каждое начало своего хода\nвраг снимает - 10 карт со столба здоровья,\n(без учета защиты врага).\nАтака по зверям: если в первую сваю атаку\nвы кинули кубик на 4 или выше вы убиваете\nзверя с одного хода атаки. Если нет вы\nдеретес со зверям согласно его описанию.",
      "cardUid": null,
      "cardKey": "club",
      "uid": "t3",
      "x": 1222,
      "y": 949,
      "w": 361,
      "h": 223
    },
    {
      "page": 1,
      "text": "Бусы телепортации.\nБазовая карта для любого класса. (одноразово)\nЕсли вы кините кубик 1 раз не менее 2-х то вы\nтелепортируетесь на клетку где вы появились В\nначале всей своей партии.\nДля заряда бус телепортации, обратитесь к\nшаману.",
      "cardUid": null,
      "cardKey": "teleport_beads",
      "uid": "t4",
      "x": 885,
      "y": 1504,
      "w": 379,
      "h": 170
    },
    {
      "page": 2,
      "text": "Клубок сплетенной нити из шерсти барана.\nИнгредиент для создания оружия, легких\nдоспех, предметов UT. Д.\nСм. Согласно требованиям чертежей или\nрецептов.",
      "cardUid": null,
      "cardKey": "yarn",
      "uid": "t6",
      "x": 99,
      "y": 976,
      "w": 355,
      "h": 163
    },
    {
      "page": 2,
      "text": "Кавер шамана.\nНеотемлимый Ингредиент для обрядов\nи изделий шамана. При обычном\nиспользовании ковра шаман каждое\nначало своего хода прибовляет себе на\nстолб здоровья +2 карты. Остальное\nиспользование ковра см. согласно\nтребованиям рецептов.",
      "cardUid": null,
      "cardKey": "shaman_carpet",
      "uid": "t7",
      "x": 854,
      "y": 933,
      "w": 494,
      "h": 211
    },
    {
      "page": 2,
      "text": "Базовый Рецепт на кавер шамана\nНеобходимые материалы для изготовления предмета\nшкура медведя: 1 карта. Сплетенная нить из шкуры\nбарана: 1 карта. Пусть шаман кинет кубик 1 раз не\nменее 3-х Если шаман не сможет кинуть нужное\nколичество за 2-е попытки, все материалы просто\nзамешиваться в свои колоды обратно, а базовый\nрецепт остается. В случии успеха шаман открывает\nрецепт и забирает изделия.",
      "cardUid": null,
      "cardKey": "recipe_shaman_carpet",
      "uid": "t8",
      "x": 1422,
      "y": 1396,
      "w": 349,
      "h": 218
    },
    {
      "page": 3,
      "text": "Очищеная Шкура Барана\nПрименимо к чертетежам и рецептам",
      "cardUid": null,
      "cardKey": "sheep_hide_c",
      "uid": "t9",
      "x": 121,
      "y": 403,
      "w": 331,
      "h": 154
    },
    {
      "page": 3,
      "text": "Шерсть барана\nКомпонент для создания нити\nКинте кубик 1 раз не менее 2-х и компонент можно открыть и забрать 1\nкарту клубок сплетенной нити.",
      "cardUid": null,
      "cardKey": "sheep_wool",
      "uid": "t10",
      "x": 1147,
      "y": 350,
      "w": 321,
      "h": 172
    },
    {
      "page": 3,
      "text": "Шкура барана\nПрименима к изделиям см. со’тасно требованиям чеотежей и рецептов,\nили кинте кубик 1 раз He менее 2-х и заберите 1-карту шерсти борана и1-у\nкарту очищеную шкуру борача",
      "cardUid": null,
      "cardKey": "sheep_hide_r",
      "uid": "t11",
      "x": 472,
      "y": 924,
      "w": 379,
      "h": 160
    },
    {
      "page": 3,
      "text": "Боран.\nКиньте кубик 2-а раза He менее 1-го или 1 раз\nHe менее 3-х и заберите 1-карту шкура борана.\nКогда вы начинаете драться с бананом, вы\nв начале своего хода снимаете по 1 карте со\nсвоего столба здоровья.",
      "cardUid": null,
      "cardKey": "sheep_ram",
      "uid": "t12",
      "x": 94,
      "y": 1399,
      "w": 366,
      "h": 204
    },
    {
      "page": 4,
      "text": "Рецепт на мешок.\nНеобходимые материалы для изготовления предмета:\nКлубок сплетенной нити из шерсти барана - 1 карта.\nОчищения шкура барана - 1 карта.\nПусть помогник кузнеца кинет кубик 2 раза не менее 3.\nПосле выполнения условий персонаж забирает карту мешок.",
      "cardUid": null,
      "cardKey": "recipe_sack",
      "uid": "t13",
      "x": 40,
      "y": 808,
      "w": 424,
      "h": 197
    },
    {
      "page": 4,
      "text": "Мешок.\nПримените эту карту\nстоя на любой точке добычи.\nВы забираете с одного кубика,\nвне зависимости от того\nсколько на нем выпадет очков,\nпо 2 карты.",
      "cardUid": null,
      "cardKey": "sack",
      "uid": "t14",
      "x": 1192,
      "y": 823,
      "w": 291,
      "h": 192
    },
    {
      "page": 7,
      "text": "Чертёж на палаток\nКласс: кузнец\nНеобходимые материалы для\nизготовления предмета: смешная\nжелезная руда - 1 карта. Пусть кузнец\nкинет кубик 2-а раза не менее 2-х.\nЕсли кузнец не сможет кинуть нужное\nколичество за 4 попытки он может\nпопробовать ewe. В случии успеха кузнец\nоткрывает чертёж и заберает молоток",
      "cardUid": null,
      "cardKey": "bp_hammer_base",
      "uid": "t15",
      "x": 58,
      "y": 299,
      "w": 375,
      "h": 234
    },
    {
      "page": 7,
      "text": "Палаток\nКласс: кузнец\nПримените этот предмет при изготовлении чертежа:\nвсе требования уменьшаются на 2.\nПример чертежа: киньте кубик 2 раза не менее 3.\nС палатком: киньте кубик 1 раз не менее 2.\nАтака по врагу: киньте кубик не менее 4\nи нанесите врагу 30 урона вме зависимости от брани врага,",
      "cardUid": null,
      "cardKey": "hammer",
      "uid": "t16",
      "x": 941,
      "y": 286,
      "w": 422,
      "h": 211
    },
    {
      "page": 8,
      "text": "Железная руда среднего качества.\n(ингредиент)\nПримените эту карту в драке с противникам:\nвыложите эту карту рубашкой вверх\nи если противник атаковал Вас первым\nто вы сначала переворачиваете\nэту карту описанием вверх\nапотом кладете её обратно\nсебе в инвентарь. После этого\nВы можете взять 2 карты с любой колоды,\nне находясь на этой точки,\nмо выбрать и забрать только одну\n(32 исключения колод чертежа и рецепты),\nвторую карту вы замещиваете\nобратно в соответствующую колоду.\nМожно использовать один раз в драке.",
      "cardUid": null,
      "cardKey": "art_mixed_001",
      "uid": "t17",
      "x": 469,
      "y": 215,
      "w": 359,
      "h": 379
    },
    {
      "page": 8,
      "text": "Грязная мли смешенная железная руда.\n(ингредиент)\nПримените эту карту в драке с противникам:\nвыложите эту карту рубашкой вверх\nи ёсли протианик атаковал Вас первым то Bы сначала\nпереворачиваете эту карту описанием вверх\nа потом кладете её обратно себе в инвентарь.\nПосле этого Вы можете взять карту с любой колоды,\nне находясь на этой точки (за исключения колод чертежа и рецепты)\nМожно использовать один раз в драке",
      "cardUid": null,
      "cardKey": "",
      "uid": "t18",
      "x": 77,
      "y": 835,
      "w": 389,
      "h": 272
    },
    {
      "uid": "t19",
      "page": 14,
      "x": 849,
      "y": 275,
      "w": 422,
      "h": 260,
      "text": "Сухой череп или череп.\n(ингредиент)\nПримените эту карту в драке\nс дварфом и дварф отходит от вас\nна 7 бордов в противоположную сторону от вас.\nПосле применения вы кладете\nэту карту обратно себе в инвентарь.\n(Можно применить один раз в драке).",
      "cardUid": null,
      "cardKey": "art_mixed_003"
    },
    {
      "uid": "t20",
      "page": 14,
      "x": 866,
      "y": 1303,
      "w": 383,
      "h": 234,
      "text": "Очищеная шкура зверя.\nИнгредиент для изготовления\nпредмета. См. Согласно\nтребованиям чертежа, рецепта. Или\nпусть шаман или помошник кузнеца\nкинет кубик 1 раз не менее 2-х и\nзабирет 1-у карту кожаный ласкут.",
      "cardUid": null,
      "cardKey": "hide_red"
    },
    {
      "uid": "t21",
      "page": 15,
      "x": 489,
      "y": 365,
      "w": 366,
      "h": 151,
      "text": "Шкура убитого зверя.\nКласс шаман\nЕсли не применять для изделия, пусть шаман кинет\nкубик 1 раз не менее 2-х и забирет 1-карту очищеной\nкожи убитого зверя.",
      "cardUid": null,
      "cardKey": "art_mixed_005"
    },
    {
      "uid": "t22",
      "page": 18,
      "x": 1023,
      "y": 1333,
      "w": 386,
      "h": 211,
      "text": "Малый золотой самородок.\n(ингредиент)\nЕсли Вы сбросите эту карту обратно в свою колоду,\nто вы лечите себя на 20 карт столба здоровья.\n(одноразовое применение) -\nпосле применения эта карта замешивается\nв свою колоду обратно.",
      "cardUid": null,
      "cardKey": "gold_nugget"
    }
  ]
}